ingot_http/__init__.py
ingot_http/bootstrap/__init__.py
ingot_http/bootstrap/base.py
ingot_http/bootstrap/scaffolding/__init__.py
ingot_http/contrib/__init__.py
ingot_http/scripts/__init__.py
ingot_http/scripts/ingot_http.py
ingot_http/tests/__init__.py
ingot_http/tests/functionals/__init__.py
ingot_http/tests/units/__init__.py
ingot_http/tests/units/bootstrap/__init__.py
ingot_http/tests/units/bootstrap/test_base.py
ingot_http/tests/units/contrib/__init__.py
ingot_http/tests/units/scripts/__init__.py
ingot_http/tests/units/scripts/test_ingot_http.py
ingot_http-0.1.0.dist-info/LICENSE
ingot_http-0.1.0.dist-info/METADATA
ingot_http-0.1.0.dist-info/WHEEL
ingot_http-0.1.0.dist-info/entry_points.txt
ingot_http-0.1.0.dist-info/top_level.txt
ingot_http-0.1.0.dist-info/RECORD
